grok/__init__.py
grok/components.py
grok/configure.zcml
grok/default.zcml
grok/dependencies.zcml
grok/events.py
grok/ftesting.zcml
grok/generations.py
grok/interfaces.py
grok/meta.zcml
grok/testing.py
grok/util.py
grok/ftests/__init__.py
grok/ftests/test_grok_functional.py
grok/ftests/catalog/__init__.py
grok/ftests/catalog/addform.py
grok/ftests/chameleon/__init__.py
grok/ftests/chameleon/chameleon_available.py
grok/ftests/chameleon/templates/available.cpt
grok/ftests/errorviews/__init__.py
grok/ftests/errorviews/errorviews.py
grok/ftests/form/__init__.py
grok/ftests/form/form.py
grok/ftests/forms/__init__.py
grok/ftests/forms/forms.py
grok/ftests/forms/templates/master.pt
grok/ftests/lifecycle/__init__.py
grok/ftests/lifecycle/create_application.py
grok/ftests/lifecycle/lifecycle_events.py
grok/ftests/security/__init__.py
grok/ftests/security/grok_view.py
grok/ftests/security/groups.py
grok/ftests/security/handle_exception.py
grok/ftests/security/preserve_permissions.py
grok/ftests/security/roles.py
grok/ftests/security/security_view.py
grok/ftests/site/__init__.py
grok/ftests/site/site.py
grok/ftests/traversal/__init__.py
grok/ftests/traversal/containertraverse.py
grok/ftests/traversal/containertraverser.py
grok/ftests/traversal/items_before_views.py
grok/ftests/traversal/modeltraverse.py
grok/ftests/traversal/traversableattr.py
grok/ftests/traversal/traverser.py
grok/ftests/traversal/traverser_sets_parent.py
grok/ftests/url/__init__.py
grok/ftests/url/application.py
grok/ftests/viewlet/__init__.py
grok/ftests/viewlet/viewlet_security.py
grok/ftests/viewlet/viewlet_security_templates/caveview.pt
grok/templates/default_display_form.pt
grok/templates/default_edit_form.pt
grok/tests/__init__.py
grok/tests/test_grok.py
grok/tests/adapter/__init__.py
grok/tests/adapter/adapter.py
grok/tests/adapter/adapterdecorator.py
grok/tests/adapter/alphabetical.py
grok/tests/adapter/classcontext.py
grok/tests/adapter/classcontextimported.py
grok-6.1.dist-info/licenses/LICENSE.txt
grok-6.1.dist-info/METADATA
grok-6.1.dist-info/WHEEL
grok-6.1.dist-info/top_level.txt
grok-6.1.dist-info/RECORD
