Metadata-Version: 2.4
Name: grok
Version: 6.1
Summary: Grok: Now even cavemen can use Zope 3!
Home-page: https://github.com/zopefoundation/grok
Author: Grok Team
Author-email: zope-dev@zope.dev
License: ZPL
Classifier: Development Status :: 5 - Production/Stable
Classifier: Environment :: Web Environment
Classifier: Intended Audience :: Developers
Classifier: License :: OSI Approved :: Zope Public License
Classifier: Programming Language :: Python
Classifier: Natural Language :: English
Classifier: Operating System :: OS Independent
Classifier: Topic :: Internet :: WWW/HTTP
Classifier: Framework :: Zope :: 3
Classifier: Programming Language :: Python :: 3
Classifier: Programming Language :: Python :: 3.9
Classifier: Programming Language :: Python :: 3.10
Classifier: Programming Language :: Python :: 3.11
Classifier: Programming Language :: Python :: 3.12
Classifier: Programming Language :: Python :: 3.13
Classifier: Programming Language :: Python :: Implementation :: CPython
Classifier: Programming Language :: Python :: Implementation :: PyPy
Requires-Python: >=3.9
License-File: LICENSE.txt
Requires-Dist: grokcore.annotation>=1.6
Requires-Dist: grokcore.catalog>=2.1
Requires-Dist: grokcore.chameleon>=1.0
Requires-Dist: grokcore.component>=3.1
Requires-Dist: grokcore.content>=1.2
Requires-Dist: grokcore.formlib>=1.10
Requires-Dist: grokcore.layout>=1.6
Requires-Dist: grokcore.message
Requires-Dist: grokcore.security[role]>=1.6
Requires-Dist: grokcore.site>=1.7
Requires-Dist: grokcore.traverser>=1.1
Requires-Dist: grokcore.view[security-publication]>=4.1
Requires-Dist: grokcore.viewlet>=1.10
Requires-Dist: martian>=1.2
Requires-Dist: pytz
Requires-Dist: setuptools
Requires-Dist: zc.catalog
Requires-Dist: ZODB
Requires-Dist: zope.annotation
Requires-Dist: zope.app.appsetup
Requires-Dist: zope.app.publication
Requires-Dist: zope.app.wsgi
Requires-Dist: zope.browserpage
Requires-Dist: zope.catalog
Requires-Dist: zope.component
Requires-Dist: zope.container
Requires-Dist: zope.contentprovider
Requires-Dist: zope.errorview[browser]
Requires-Dist: zope.event
Requires-Dist: zope.exceptions
Requires-Dist: zope.generations
Requires-Dist: zope.i18n
Requires-Dist: zope.i18nmessageid
Requires-Dist: zope.interface
Requires-Dist: zope.intid
Requires-Dist: zope.keyreference
Requires-Dist: zope.lifecycleevent
Requires-Dist: zope.location
Requires-Dist: zope.login
Requires-Dist: zope.password
Requires-Dist: zope.principalregistry
Requires-Dist: zope.publisher
Requires-Dist: zope.schema
Requires-Dist: zope.security
Requires-Dist: zope.securitypolicy
Requires-Dist: zope.site
Requires-Dist: zope.traversing
Provides-Extra: test
Requires-Dist: zope.app.wsgi[test]; extra == "test"
Requires-Dist: zope.configuration; extra == "test"
Requires-Dist: zope.testbrowser; extra == "test"
Requires-Dist: zope.testing; extra == "test"
Requires-Dist: zope.testrunner; extra == "test"
Provides-Extra: docs
Requires-Dist: Sphinx; extra == "docs"
Dynamic: author
Dynamic: author-email
Dynamic: classifier
Dynamic: description
Dynamic: home-page
Dynamic: license
Dynamic: license-file
Dynamic: provides-extra
Dynamic: requires-dist
Dynamic: requires-python
Dynamic: summary
